flexsea/__init__.py
flexsea/device.py
flexsea/utilities/__init__.py
flexsea/utilities/aws.py
flexsea/utilities/constants.py
flexsea/utilities/decorators.py
flexsea/utilities/firmware.py
flexsea/utilities/library.py
flexsea/utilities/specs.py
flexsea/utilities/system.py
flexsea-12.2.3.dist-info/LICENSE
flexsea-12.2.3.dist-info/METADATA
flexsea-12.2.3.dist-info/WHEEL
flexsea-12.2.3.dist-info/RECORD
