Metadata-Version: 2.1
Name: flexsea
Version: 12.2.3
Summary: 
Home-page: https://github.com/DephyInc/Actuator-Package
License: MIT
Author: Jared
Author-email: jcoughlin@dephy.com
Requires-Python: >=3.11,<4.0
Classifier: License :: OSI Approved :: MIT License
Classifier: Programming Language :: Python :: 3
Classifier: Programming Language :: Python :: 3.11
Classifier: Programming Language :: Python :: 3.12
Requires-Dist: boto3 (>=1.40.41,<2.0.0)
Requires-Dist: pandas (>=2.3.3,<3.0.0)
Requires-Dist: pendulum (>=2.1.2,<3.0.0) ; python_version < "3.12"
Requires-Dist: pendulum (>=3.0.0,<4.0.0) ; python_version >= "3.12"
Requires-Dist: pyudev (>=0.24.1,<0.25.0) ; sys_platform == "linux"
Requires-Dist: pyyaml (>=6.0,<7.0)
Requires-Dist: semantic-version (>=2.10.0,<3.0.0)
